Metadata-Version: 2.1
Name: mkeil
Version: 0.0.2
Summary: a library for send email
Home-page: 
Author: Mehran Karimi
Author-email: axelox9@gmail.com
License: MIT
Keywords: email sender
Classifier: Development Status :: 5 - Production/Stable
Classifier: Intended Audience :: Education
Classifier: Operating System :: Microsoft :: Windows :: Windows 10
Classifier: License :: OSI Approved :: MIT License
Classifier: Programming Language :: Python :: 3
License-File: LICENCE.txt
